flask_super/__init__.py
flask_super/cli/__init__.py
flask_super/cli/commands/__init__.py
flask_super/cli/commands/_colors.py
flask_super/cli/commands/config.py
flask_super/cli/commands/inspect.py
flask_super/decorators.py
flask_super/initializers/__init__.py
flask_super/initializers/logging.py
flask_super/registry.py
flask_super/scanner.py
flask_super/services.py
flask_super-0.2.11.dist-info/WHEEL
flask_super-0.2.11.dist-info/METADATA
flask_super-0.2.11.dist-info/RECORD
