Metadata-Version: 2.3
Name: flask-super
Version: 0.2.11
Summary: Patterns and idioms for Flask applications.
Author: Abilian SAS
Author-email: Abilian SAS <sf@abilian.com>
Classifier: Development Status :: 2 - Pre-Alpha
Classifier: Intended Audience :: Developers
Classifier: Programming Language :: Python :: 3
Classifier: Programming Language :: Python :: 3.10
Classifier: Programming Language :: Python :: 3.11
Classifier: Programming Language :: Python :: 3.12
Requires-Dist: flask>=3.0
Requires-Dist: svcs>=24.1
Requires-Dist: sentry-sdk>=2
Requires-Dist: loguru>=0.7
Requires-Python: >=3.10, <4
